dbaas/__init__.py
dbaas/openapi_client/__init__.py
dbaas/openapi_client/api_client.py
dbaas/openapi_client/api_response.py
dbaas/openapi_client/configuration.py
dbaas/openapi_client/exceptions.py
dbaas/openapi_client/py.typed
dbaas/openapi_client/rest.py
dbaas/openapi_client/api/__init__.py
dbaas/openapi_client/api/backups_api.py
dbaas/openapi_client/api/databases_api.py
dbaas/openapi_client/api/reports_api.py
dbaas/openapi_client/models/__init__.py
dbaas/openapi_client/models/change_control_panel200_response.py
dbaas/openapi_client/models/create_database200_response.py
dbaas/openapi_client/models/create_databases.py
dbaas/openapi_client/models/create_databases_options.py
dbaas/openapi_client/models/db_details.py
dbaas/openapi_client/models/db_details_database.py
dbaas/openapi_client/models/db_details_database_meta_data.py
dbaas/openapi_client/models/db_details_database_node.py
dbaas/openapi_client/models/dbs_details.py
dbaas/openapi_client/models/dbs_details_databases_inner.py
dbaas/openapi_client/models/download_backup200_response.py
dbaas/openapi_client/models/get_database_summary_reports200_response.py
dbaas/openapi_client/models/get_database_summary_reports200_response_cpu_usage_inner.py
dbaas/openapi_client/models/get_database_summary_reports200_response_cpu_usage_inner_value_inner.py
dbaas/openapi_client/models/get_database_summary_reports200_response_disks_usage_inner.py
dbaas/openapi_client/models/get_list_backups200_response.py
dbaas/openapi_client/models/get_list_backups200_response_backups_inner.py
dbaas/openapi_client/models/reports.py
dbaas/openapi_client/models/reports_result_inner.py
dbaas/openapi_client/models/resize_database_request.py
dbaas/openapi_client/models/turn_database_request.py
dns/__init__.py
dns/openapi_client/__init__.py
dns/openapi_client/api_client.py
dns/openapi_client/api_response.py
dns/openapi_client/configuration.py
dns/openapi_client/exceptions.py
dns/openapi_client/py.typed
dns/openapi_client/rest.py
jarqvi_openapi_client-9.0.0.dist-info/LICENCE
jarqvi_openapi_client-9.0.0.dist-info/METADATA
jarqvi_openapi_client-9.0.0.dist-info/WHEEL
jarqvi_openapi_client-9.0.0.dist-info/top_level.txt
jarqvi_openapi_client-9.0.0.dist-info/RECORD
